__init__.py
pixelpusher/__init__.py
pixelpusher/buttons.py
pixelpusher/colors.py
pixelpusher/matrix.py
pixel_multiverse-0.5.2.dist-info/LICENSE
pixel_multiverse-0.5.2.dist-info/METADATA
pixel_multiverse-0.5.2.dist-info/WHEEL
pixel_multiverse-0.5.2.dist-info/top_level.txt
pixel_multiverse-0.5.2.dist-info/RECORD
