Metadata-Version: 2.1
Name: pixel-multiverse
Version: 0.5.2
Summary: Pixel pusher for Pimoroni Multiverse LED products
Author-email: Emma Laurijssens van Engelenhoven <emma@emma.ee>
Project-URL: Homepage, https://github.com/elaurijssens/pixel-multiverse
Project-URL: Issues, https://github.com/elaurijssens/pixel-multiverse/issues
Project-URL: Release Notes, https://github.com/elaurijssens/pixel-multiverse/blob/main/release-notes.md
Classifier: Programming Language :: Python :: 3
Classifier: License :: OSI Approved :: MIT License
Classifier: Operating System :: OS Independent
Requires-Python: >=3.11
License-File: LICENSE
Requires-Dist: pyserial
Requires-Dist: pillow
